<?xml version="1.0" encoding="utf-8" ?>
<dwsync>
<file name="CellEntry.php" server="test.look-estates.com" local="128817510600000000" remote="128817510600000000" />
<file name="CellFeed.php" server="test.look-estates.com" local="128817510600000000" remote="128817510600000000" />
<file name="CellQuery.php" server="test.look-estates.com" local="128817510600000000" remote="128817510600000000" />
<file name="DocumentQuery.php" server="test.look-estates.com" local="128817510600000000" remote="128817510600000000" />
<file name="ListEntry.php" server="test.look-estates.com" local="128817510600000000" remote="128817510600000000" />
<file name="ListFeed.php" server="test.look-estates.com" local="128817510600000000" remote="128817510600000000" />
<file name="ListQuery.php" server="test.look-estates.com" local="128817510600000000" remote="128817510600000000" />
<file name="SpreadsheetEntry.php" server="test.look-estates.com" local="128817510600000000" remote="128817510600000000" />
<file name="SpreadsheetFeed.php" server="test.look-estates.com" local="128817510600000000" remote="128817510600000000" />
<file name="WorksheetEntry.php" server="test.look-estates.com" local="128817510600000000" remote="128817510600000000" />
<file name="WorksheetFeed.php" server="test.look-estates.com" local="128817510600000000" remote="128817510600000000" />
</dwsync>